odoo/addons/l10n_eu_oss_oca/README.rst
odoo/addons/l10n_eu_oss_oca/__init__.py
odoo/addons/l10n_eu_oss_oca/__manifest__.py
odoo/addons/l10n_eu_oss_oca/data/oss.tax.rate.csv
odoo/addons/l10n_eu_oss_oca/i18n/es.po
odoo/addons/l10n_eu_oss_oca/i18n/fr_FR.po
odoo/addons/l10n_eu_oss_oca/i18n/it.po
odoo/addons/l10n_eu_oss_oca/i18n/l10n_eu_oss.pot
odoo/addons/l10n_eu_oss_oca/i18n/l10n_eu_oss_oca.pot
odoo/addons/l10n_eu_oss_oca/i18n/pt_PT.po
odoo/addons/l10n_eu_oss_oca/models/__init__.py
odoo/addons/l10n_eu_oss_oca/models/account_fiscal_position.py
odoo/addons/l10n_eu_oss_oca/models/account_tax.py
odoo/addons/l10n_eu_oss_oca/models/oss_tax_rate.py
odoo/addons/l10n_eu_oss_oca/readme/CONFIGURE.md
odoo/addons/l10n_eu_oss_oca/readme/CONTRIBUTORS.md
odoo/addons/l10n_eu_oss_oca/readme/DESCRIPTION.md
odoo/addons/l10n_eu_oss_oca/readme/ROADMAP.md
odoo/addons/l10n_eu_oss_oca/readme/USAGE.md
odoo/addons/l10n_eu_oss_oca/security/ir.model.access.csv
odoo/addons/l10n_eu_oss_oca/static/description/icon.png
odoo/addons/l10n_eu_oss_oca/static/description/index.html
odoo/addons/l10n_eu_oss_oca/tests/__init__.py
odoo/addons/l10n_eu_oss_oca/tests/test_l10n_eu_oss.py
odoo/addons/l10n_eu_oss_oca/views/account_fiscal_position_views.xml
odoo/addons/l10n_eu_oss_oca/views/res_config_settings.xml
odoo/addons/l10n_eu_oss_oca/wizard/__init__.py
odoo/addons/l10n_eu_oss_oca/wizard/l10n_eu_oss_wizard.py
odoo/addons/l10n_eu_oss_oca/wizard/l10n_eu_oss_wizard.xml
odoo_addon_l10n_eu_oss_oca-18.0.1.0.0.2.dist-info/METADATA
odoo_addon_l10n_eu_oss_oca-18.0.1.0.0.2.dist-info/WHEEL
odoo_addon_l10n_eu_oss_oca-18.0.1.0.0.2.dist-info/top_level.txt
odoo_addon_l10n_eu_oss_oca-18.0.1.0.0.2.dist-info/RECORD
