Metadata-Version: 2.1
Name: odoo-addon-l10n_eu_oss_oca
Version: 18.0.1.0.0.2
Requires-Python: >=3.10
Requires-Dist: odoo-addon-account_fiscal_position_partner_type==18.0.*
Requires-Dist: odoo==18.0.*
Summary: L10n EU OSS OCA
Home-page: https://github.com/OCA/account-fiscal-rule
License: AGPL-3
Author: Sygel Technology,Odoo Community Association (OCA)
Author-email: support@odoo-community.org
Classifier: Programming Language :: Python
Classifier: Framework :: Odoo
Classifier: Framework :: Odoo :: 18.0
Classifier: License :: OSI Approved :: GNU Affero General Public License v3
Classifier: Development Status :: 5 - Production/Stable
